Metadata-Version: 2.1
Name: lexi_xray
Version: 0.5.0
Summary: Data analysis tools for the Lexi project
Home-page: https://github.com/Lexi-BU/lexi
Author: Ramiz Qudsi
Author-email: lunar.lexi01@gmail.com
License: GPLv3
Keywords: data analysis
Classifier: Development Status :: 4 - Beta
Classifier: Intended Audience :: Science/Research
Classifier: License :: OSI Approved :: GNU General Public License v3 (GPLv3)
Classifier: Programming Language :: Python :: 3
Classifier: Programming Language :: Python :: 3.10
Classifier: Topic :: Scientific/Engineering :: Information Analysis
Requires-Python: >=3.10
License-File: LICENSE
Requires-Dist: toml
Requires-Dist: pandas
Requires-Dist: pytest
Requires-Dist: cdflib
Requires-Dist: matplotlib
Requires-Dist: jupyter
